cycIFAAP/FiReTiTiLiB.jar
cycIFAAP/__init__.py
cycIFAAP/cycIFAAP.py
cycIFAAP/Restore/RESTORE/RESTORE.py
cycIFAAP/Restore/RESTORE/__init__.py
cycIFAAP/Restore/ssc/cluster/__init__.py
cycIFAAP/Restore/ssc/cluster/selfrepresentation.py
cycIFAAP/lib/FiReTiTiCoreJava.jar
cycIFAAP/lib/JSAT-0.0.2.jar
cycIFAAP/lib/JTransforms-3.1-with-dependencies.jar
cycIFAAP/lib/Jama-1.0.2.jar
cycIFAAP/lib/bioformats_package.jar
cycIFAAP/lib/common-image-3.8.1.jar
cycIFAAP/lib/common-io-3.8.1.jar
cycIFAAP/lib/common-lang-3.8.1.jar
cycIFAAP/lib/commons-math-1.0.jar
cycIFAAP/lib/flanagan.jar
cycIFAAP/lib/guava-30.1.1-jre.jar
cycIFAAP/lib/ij.jar
cycIFAAP/lib/imageio-bmp-3.8.1.jar
cycIFAAP/lib/imageio-core-3.8.1.jar
cycIFAAP/lib/imageio-iff-3.8.1.jar
cycIFAAP/lib/imageio-jpeg-3.8.1.jar
cycIFAAP/lib/imageio-metadata-3.8.1.jar
cycIFAAP/lib/imageio-pnm-3.8.1.jar
cycIFAAP/lib/imageio-tiff-3.9.0-20220504.163059-23.jar
cycIFAAP/lib/imageio-webp-3.8.1.jar
cycIFAAP/lib/imagescience.jar
cycIFAAP/lib/jai_codec.jar
cycIFAAP/lib/jai_core.jar
cycIFAAP/lib/java-image-scaling-0.8.6.jar
cycIFAAP/lib/jdom-2.0.5.jar
cycIFAAP/lib/quickhull3d.jar
cycIFAAP/lib/xstream-1.4.6.jar
cycIFAAP-5.7.7.dist-info/METADATA
cycIFAAP-5.7.7.dist-info/WHEEL
cycIFAAP-5.7.7.dist-info/top_level.txt
cycIFAAP-5.7.7.dist-info/RECORD
