Metadata-Version: 2.1
Name: cycIFAAP
Version: 5.7.7
Summary: Cyclic ImmunoFluoresence (cycIF) Automatic Analysis Pipeline
Home-page: https://www.thibault.biz/Research/cycIFAAP/cycIFAAP.html
Download-URL: https://www.thibault.biz/Doc/cycIFAAP/cycIFAAP-5.7.7.tar.gz
Author: Guillaume THIBAULT, Erik Burlingame, Young Hwan Chang
Author-email: thibaulg@ohsu.edu, chanyo@ohsu.edu
Maintainer: Guillaume THIBAULT
Maintainer-email: thibaulg@ohsu.edu
License: MIT
Keywords: cyclic Immunofluorescence,cycif,immunofluorescence,registration,segmentation,features,features extraction,restore,napari,nuclei,nucleus,cells,cell,cell analysis,cell type
Classifier: Development Status :: 5 - Production/Stable
Classifier: Environment :: Console
Classifier: Environment :: GPU
Classifier: Environment :: GPU :: NVIDIA CUDA :: 10.2
Classifier: Environment :: Other Environment
Classifier: Intended Audience :: Developers
Classifier: Intended Audience :: Healthcare Industry
Classifier: Intended Audience :: Science/Research
Classifier: License :: OSI Approved :: MIT License
Classifier: Operating System :: OS Independent
Classifier: Programming Language :: Java
Classifier: Programming Language :: Python :: 3
Classifier: Programming Language :: Python :: 3.8
Classifier: Programming Language :: Python :: 3.9
Classifier: Topic :: Scientific/Engineering
Classifier: Topic :: Scientific/Engineering :: Artificial Intelligence
Classifier: Topic :: Scientific/Engineering :: Bio-Informatics
Classifier: Topic :: Scientific/Engineering :: Image Processing
Classifier: Topic :: Scientific/Engineering :: Image Recognition
Requires-Python: >=3.8,<3.10
Requires-Dist: FiReTiTiPyLib (>=1.5.5)
Requires-Dist: cellpose (<2.0,>=1.0.2)
Requires-Dist: DeepCell (>=0.12.0)
Requires-Dist: numpy (>=1.22.4)
Requires-Dist: torch (<1.8,>=1.7.1)
Requires-Dist: torchvision (<0.9,>=0.8.2)
